vqcloud/__init__.py
vqcloud/_version.py
vqcloud/abstract_result.py
vqcloud/annealing.py
vqcloud/api.py
vqcloud/data.py
vqcloud/datafactory.py
vqcloud/device.py
vqcloud/local.py
vqcloud/task.py
vqcloud/device_specific/__init__.py
vqcloud/device_specific/aws_device.py
v_quantum_cloud-0.0.3.dist-info/METADATA
v_quantum_cloud-0.0.3.dist-info/WHEEL
v_quantum_cloud-0.0.3.dist-info/top_level.txt
v_quantum_cloud-0.0.3.dist-info/RECORD
