Metadata-Version: 2.1
Name: v-quantum-cloud
Version: 0.0.3
Summary: V-Quantum cloud library for everyone, product of V-Quantum Technology
Home-page: https://github.com/C2iteam/v-quantum-cloud.git
Author: The v_quantum_cloud Developers
Author-email: info@v-quantum-technology.com
License: Apache 2
Classifier: Development Status :: 3 - Alpha
Classifier: License :: OSI Approved :: Apache Software License
Classifier: Programming Language :: Python :: 3.7
Classifier: Programming Language :: Python :: 3.8
Classifier: Programming Language :: Python :: 3.9
Classifier: Programming Language :: Python :: 3.10
Requires-Dist: blueqat (>=0.4.9)
Requires-Dist: braket-backend-blueqat (>=0.0.5)
Requires-Dist: amazon-braket-sdk (>=1.5.13)
Requires-Dist: pandas (>=1.2)
